{"id": 16849, "mbti_profile": "Rich Goranski", "profile_name_searchable": "richgoranski", "allow_commenting": true, "allow_voting": true, "user_id": 6937, "contributor": "angelinaemanuel7", "contributor_create_date": "2018-10-12 22:18:27", "contributor_pic_path": "https://lh3.googleusercontent.com/a-/AOh14GjT_uxtBFFHhGlGip1oam6WJhmTeRLLDhwb8JHcKQ=s96-c", "display_order": 0, "edit_lock": 0, "edit_lock_picture": 0, "is_active": true, "is_approved": true, "mbti_enneagram_type": "ESFP 3w4", "mbti_type": "ESFP 3w4", "pdb_comment_access": true, "pdb_page_owner": 0, "pdb_public_access": true, "wiki_description": "A popular kid who's as short as he is terrifying. He kicks off the plot by telling Jeremy to buy a SQUIP.", "watch_count": 26, "comment_count": 3, "vote_count": 38, "vote_count_enneagram": 16, "vote_count_mbti": 38, "total_vote_counts": 72, "personality_type": "ESFP - 3w4 - 386 - SLE - SLUEI - Choleric [Dominant]", "type_updated_date": "2021-05-20 01:21:33", "enneagram_vote": "", "enneagram_vote_id": 0, "mbti_vote": "", "mbti_vote_id": 0, "is_watching": false, "image_exists": false, "profile_image_url": "https://static1.personality-database.com/profile_images/77b7a1a2972a495c91d0067578a4f124.png", "profile_image_credit": "", "profile_image_credit_id": 56520, "profile_image_credit_type": "0", "profile_image_credit_url": "", "alt_subcategory": "", "related_subcategories": "", "cat_id": 13, "category": "Theatre", "category_is_fictional": true, "sub_cat_id": 1846, "subcategory": "Be More Chill", "subcat_link_info": {"sub_cat_id": 1846, "cat_id": 13, "property_id": 2, "subcategory": "Be More Chill"}, "related_subcat_link_info": null, "related_profiles": [{"id": 14895, "mbti_profile": "Jeremy Heere", "subcategory": "Be More Chill", "profile_image_url": "https://static1.personality-database.com/profile_images/92e7043c79e74c818d82453fa215be32.png", "profile_name": "Jeremy Heere", "profile_subcat": "Be More Chill", "sub_cat_id": 1846, "cat_id": 13, "property_id": 2, "mbti": "INTP", "enneatype": "6w5"}, {"id": 16846, "mbti_profile": "The SQUIP", "subcategory": "Be More Chill", "profile_image_url": "https://static1.personality-database.com/profile_images/befe89d823814e27908f920b49448760.png", "profile_name": "The SQUIP", "profile_subcat": "Be More Chill", "sub_cat_id": 1846, "cat_id": 13, "property_id": 2, "mbti": "ENTJ", "enneatype": "3w2"}, {"id": 14896, "mbti_profile": "Michael Mell", "subcategory": "Be More Chill", "profile_image_url": "https://static1.personality-database.com/profile_images/d5a601a1bc4b4a7eb88ae550715c3956.png", "profile_name": "Michael Mell", "profile_subcat": "Be More Chill", "sub_cat_id": 1846, "cat_id": 13, "property_id": 2, "mbti": "ISFP", "enneatype": "6w7"}, {"id": 14897, "mbti_profile": "Christine Canigula", "subcategory": "Be More Chill", "profile_image_url": "https://static1.personality-database.com/profile_images/a3235c3ee95e49e394f791435f932694.png", "profile_name": "Christine Canigula", "profile_subcat": "Be More Chill", "sub_cat_id": 1846, "cat_id": 13, "property_id": 2, "mbti": "ENFP", "enneatype": "7w6"}, {"id": 16845, "mbti_profile": "Chloe Valentine", "subcategory": "Be More Chill", "profile_image_url": "https://static1.personality-database.com/profile_images/b802c1a0c5264fce95ebbea6dd7ee1ba.png", "profile_name": "Chloe Valentine", "profile_subcat": "Be More Chill", "sub_cat_id": 1846, "cat_id": 13, "property_id": 2, "mbti": "ESFJ", "enneatype": "3w4"}, {"id": 16847, "mbti_profile": "Brooke Lohst", "subcategory": "Be More Chill", "profile_image_url": "https://static1.personality-database.com/profile_images/ef93d9b9f7e4483c9e350174aa5f6b81.png", "profile_name": "Brooke Lohst", "profile_subcat": "Be More Chill", "sub_cat_id": 1846, "cat_id": 13, "property_id": 2, "mbti": "ESFJ", "enneatype": "6w7"}, {"id": 16853, "mbti_profile": "Jake Dillinger", "subcategory": "Be More Chill", "profile_image_url": "https://static1.personality-database.com/profile_images/69ee5d49c2354a15a907a6290f10384a.png", "profile_name": "Jake Dillinger", "profile_subcat": "Be More Chill", "sub_cat_id": 1846, "cat_id": 13, "property_id": 2, "mbti": "ESFP", "enneatype": "3w4"}, {"id": 16850, "mbti_profile": "Jenna Rolan", "subcategory": "Be More Chill", "profile_image_url": "https://static1.personality-database.com/profile_images/b69caf461d8a4a2fbda56ab1436485dc.png", "profile_name": "Jenna Rolan", "profile_subcat": "Be More Chill", "sub_cat_id": 1846, "cat_id": 13, "property_id": 2, "mbti": "ESTP", "enneatype": "7w8"}], "functions": ["Se", "Fi", "Te", "Ni"], "systems": [{"hex_color": "#888888", "id": 1, "personality_type": "XXXX", "personality_type_id": 0, "system_name": "Four Letter", "system_vote_count": 38, "user_vote_type_id": 0, "vote_id": 0}, {"hex_color": "#006775", "id": 2, "personality_type": "XXXX", "personality_type_id": 0, "system_name": "Enneagram", "system_vote_count": 16, "user_vote_type_id": 0, "vote_id": 0}, {"hex_color": "#006775", "id": 5, "personality_type": "XXXX", "personality_type_id": 0, "system_name": "Instinctual Variant", "system_vote_count": 4, "user_vote_type_id": 0, "vote_id": 0}, {"hex_color": "#006775", "id": 6, "personality_type": "XXXX", "personality_type_id": 0, "system_name": "Tritype", "system_vote_count": 3, "user_vote_type_id": 0, "vote_id": 0}, {"hex_color": "#888888", "id": 3, "personality_type": "XXXX", "personality_type_id": 0, "system_name": "Socionics", "system_vote_count": 2, "user_vote_type_id": 0, "vote_id": 0}, {"hex_color": "#888888", "id": 9, "personality_type": "XXXX", "personality_type_id": 0, "system_name": "Big 5 (SLOAN)", "system_vote_count": 2, "user_vote_type_id": 0, "vote_id": 0}, {"hex_color": "#888888", "id": 8, "personality_type": "XXXX", "personality_type_id": 0, "system_name": "Attitudinal Psyche", "system_vote_count": 3, "user_vote_type_id": 0, "vote_id": 0}, {"hex_color": "#888888", "id": 7, "personality_type": "XXXX", "personality_type_id": 0, "system_name": "Temperaments", "system_vote_count": 4, "user_vote_type_id": 0, "vote_id": 0}, {"hex_color": "#888888", "id": 11, "personality_type": "XXXX", "personality_type_id": 0, "system_name": "Classic Jungian", "system_vote_count": 0, "user_vote_type_id": 0, "vote_id": 0}], "breakdown_systems": {"1": [{"myValue": "ESFP", "personality_system_id": 1, "personality_type": "ESFP", "theCount": 22}, {"myValue": "ESTP", "personality_system_id": 1, "personality_type": "ESTP", "theCount": 8}, {"myValue": "ENFP", "personality_system_id": 1, "personality_type": "ENFP", "theCount": 5}, {"myValue": "ENTP", "personality_system_id": 1, "personality_type": "ENTP", "theCount": 1}, {"myValue": "INFP", "personality_system_id": 1, "personality_type": "INFP", "theCount": 1}, {"myValue": "ISFP", "personality_system_id": 1, "personality_type": "ISFP", "theCount": 1}], "11": [{"myValue": "XXXX", "personality_system_id": 0, "personality_type": "XXXX", "theCount": 0}], "2": [{"myValue": "3w4", "personality_system_id": 2, "personality_type": "3w4", "theCount": 11}, {"myValue": "8w7", "personality_system_id": 2, "personality_type": "8w7", "theCount": 2}, {"myValue": "3w2", "personality_system_id": 2, "personality_type": "3w2", "theCount": 1}, {"myValue": "4w5", "personality_system_id": 2, "personality_type": "4w5", "theCount": 1}, {"myValue": "6w5", "personality_system_id": 2, "personality_type": "6w5", "theCount": 1}], "3": [{"myValue": "SEE", "personality_system_id": 3, "personality_type": "SEE", "theCount": 1}, {"myValue": "SLE", "personality_system_id": 3, "personality_type": "SLE", "theCount": 1}], "5": [{"myValue": "sp/so", "personality_system_id": 5, "personality_type": "sp/so", "theCount": 1}, {"myValue": "sp/sx", "personality_system_id": 5, "personality_type": "sp/sx", "theCount": 1}, {"myValue": "sx/so", "personality_system_id": 5, "personality_type": "sx/so", "theCount": 1}, {"myValue": "sx/sp", "personality_system_id": 5, "personality_type": "sx/sp", "theCount": 1}], "6": [{"myValue": "386", "personality_system_id": 6, "personality_type": "386", "theCount": 2}, {"myValue": "378", "personality_system_id": 6, "personality_type": "378", "theCount": 1}], "7": [{"myValue": "Choleric [Dominant]", "personality_system_id": 7, "personality_type": "Choleric [Dominant]", "theCount": 2}, {"myValue": "Choleric-Sanguine", "personality_system_id": 7, "personality_type": "Choleric-Sanguine", "theCount": 1}, {"myValue": "Sanguine [Dominant]", "personality_system_id": 7, "personality_type": "Sanguine [Dominant]", "theCount": 1}], "8": [{"myValue": "FVEL", "personality_system_id": 8, "personality_type": "FVEL", "theCount": 2}, {"myValue": "EVFL", "personality_system_id": 8, "personality_type": "EVFL", "theCount": 1}], "9": [{"myValue": "SLUEI", "personality_system_id": 9, "personality_type": "SLUEI", "theCount": 1}, {"myValue": "SLUEN", "personality_system_id": 9, "personality_type": "SLUEN", "theCount": 1}]}, "breakdown_config": {"expand": {"1": 3, "11": 1, "2": 3, "3": 1, "5": 1, "6": 1, "7": 1, "8": 1, "9": 1}, "fire": {"1": 0, "11": 0, "2": 0, "3": 0, "5": 0, "6": 0, "7": 0, "8": 0, "9": 0}}, "mbti_letter_stats": [{"type": "E", "percentage": "95%", "PercentageFloat": 0.9473684210526315}, {"type": "S", "percentage": "82%", "PercentageFloat": 0.8157894736842105}, {"type": "F", "percentage": "76%", "PercentageFloat": 0.7631578947368421}, {"type": "P", "percentage": "100%", "PercentageFloat": 1}], "topic_info": {"can_generate": false, "topic": {"description": "", "follow_count": 0, "id": 15492, "is_following": false, "is_join_pending": false, "is_banned": false, "is_moderated": false, "name_readable": "Rich Goranski", "post_count": 0, "source_profile_id": 16849, "source_type": "profile", "join_to_post": false, "can_pin": false, "related_topics": [{"description": "", "follow_count": 0, "id": 13725, "is_following": false, "is_join_pending": false, "is_banned": false, "is_moderated": false, "name_readable": "Michael Mell", "post_count": 2, "source_profile_id": 14896, "source_type": "profile", "image": {"picURL": "https://static1.personality-database.com/profile_images/d5a601a1bc4b4a7eb88ae550715c3956.png"}, "join_to_post": false, "can_pin": false}, {"description": "", "follow_count": 0, "id": 13726, "is_following": false, "is_join_pending": false, "is_banned": false, "is_moderated": false, "name_readable": "Christine Canigula", "post_count": 1, "source_profile_id": 14897, "source_type": "profile", "image": {"picURL": "https://static1.personality-database.com/profile_images/a3235c3ee95e49e394f791435f932694.png"}, "join_to_post": false, "can_pin": false}, {"description": "", "follow_count": 1, "id": 15496, "is_following": false, "is_join_pending": false, "is_banned": false, "is_moderated": false, "name_readable": "Jake Dillinger", "post_count": 1, "source_profile_id": 16853, "source_type": "profile", "image": {"picURL": "https://static1.personality-database.com/profile_images/69ee5d49c2354a15a907a6290f10384a.png"}, "join_to_post": false, "can_pin": false}, {"description": "", "follow_count": 0, "id": 13724, "is_following": false, "is_join_pending": false, "is_banned": false, "is_moderated": false, "name_readable": "Jeremy Heere", "post_count": 0, "source_profile_id": 14895, "source_type": "profile", "image": {"picURL": "https://static1.personality-database.com/profile_images/92e7043c79e74c818d82453fa215be32.png"}, "join_to_post": false, "can_pin": false}, {"description": "", "follow_count": 0, "id": 15488, "is_following": false, "is_join_pending": false, "is_banned": false, "is_moderated": false, "name_readable": "Chloe Valentine", "post_count": 0, "source_profile_id": 16845, "source_type": "profile", "image": {"picURL": "https://static1.personality-database.com/profile_images/b802c1a0c5264fce95ebbea6dd7ee1ba.png"}, "join_to_post": false, "can_pin": false}, {"description": "", "follow_count": 0, "id": 15489, "is_following": false, "is_join_pending": false, "is_banned": false, "is_moderated": false, "name_readable": "The SQUIP", "post_count": 0, "source_profile_id": 16846, "source_type": "profile", "image": {"picURL": "https://static1.personality-database.com/profile_images/befe89d823814e27908f920b49448760.png"}, "join_to_post": false, "can_pin": false}, {"description": "", "follow_count": 0, "id": 15490, "is_following": false, "is_join_pending": false, "is_banned": false, "is_moderated": false, "name_readable": "Brooke Lohst", "post_count": 0, "source_profile_id": 16847, "source_type": "profile", "image": {"picURL": "https://static1.personality-database.com/profile_images/ef93d9b9f7e4483c9e350174aa5f6b81.png"}, "join_to_post": false, "can_pin": false}, {"description": "", "follow_count": 0, "id": 15491, "is_following": false, "is_join_pending": false, "is_banned": false, "is_moderated": false, "name_readable": "Mr. Heere", "post_count": 0, "source_profile_id": 16848, "source_type": "profile", "image": {"picURL": "https://static1.personality-database.com/profile_images/e38db86abb114c44870e65d4b9803d51.png"}, "join_to_post": false, "can_pin": false}, {"description": "", "follow_count": 0, "id": 15492, "is_following": false, "is_join_pending": false, "is_banned": false, "is_moderated": false, "name_readable": "Rich Goranski", "post_count": 0, "source_profile_id": 16849, "source_type": "profile", "image": {"picURL": "https://static1.personality-database.com/profile_images/77b7a1a2972a495c91d0067578a4f124.png"}, "join_to_post": false, "can_pin": false}, {"description": "", "follow_count": 0, "id": 15493, "is_following": false, "is_join_pending": false, "is_banned": false, "is_moderated": false, "name_readable": "Jenna Rolan", "post_count": 0, "source_profile_id": 16850, "source_type": "profile", "image": {"picURL": "https://static1.personality-database.com/profile_images/b69caf461d8a4a2fbda56ab1436485dc.png"}, "join_to_post": false, "can_pin": false}, {"description": "", "follow_count": 1, "id": 15494, "is_following": false, "is_join_pending": false, "is_banned": false, "is_moderated": false, "name_readable": "Scary Stockboy", "post_count": 0, "source_profile_id": 16851, "source_type": "profile", "image": {"picURL": "https://www.personality-database.com/images/profile_transparent.png"}, "join_to_post": false, "can_pin": false}, {"description": "", "follow_count": 0, "id": 15495, "is_following": false, "is_join_pending": false, "is_banned": false, "is_moderated": false, "name_readable": "Mr. Reyes", "post_count": 0, "source_profile_id": 16852, "source_type": "profile", "image": {"picURL": "https://static1.personality-database.com/profile_images/169c5fa3e95e4b559768e965fff7fe02.png"}, "join_to_post": false, "can_pin": false}], "subcategory": "Be More Chill", "topic_image_url": "https://static1.personality-database.com/profile_images/77b7a1a2972a495c91d0067578a4f124.png", "source_location": {"cid": 13, "pid": 2, "sub_cat_id": 1846}, "can_post_image": false, "can_post_audio": false, "posts": {"posts": []}}}}