{"id": 324966, "mbti_profile": "Katherine", "profile_name_searchable": "katherine", "allow_commenting": true, "allow_voting": true, "user_id": 235491, "contributor": "mercycamore", "contributor_create_date": "2021-05-20 02:25:52", "contributor_pic_path": "https://lh3.googleusercontent.com/a-/AOh14GjqGBivGx3FlkIil3sU_wo2QyYF1DhI7NbLa2gb1g=s96-c", "display_order": 990, "edit_lock": 0, "edit_lock_picture": 0, "is_active": true, "is_approved": true, "mbti_enneagram_type": "ENFJ 3w4", "mbti_type": "ENFJ 3w4", "pdb_comment_access": true, "pdb_page_owner": 0, "pdb_public_access": true, "wiki_description": "#Girlboss Approved.", "watch_count": 11, "comment_count": 2, "vote_count": 24, "vote_count_enneagram": 4, "vote_count_mbti": 24, "total_vote_counts": 35, "personality_type": "ENFJ - 3w4 - so/sp - 317 - Sanguine [Dominant]", "type_updated_date": "2022-04-12 19:55:53", "enneagram_vote": "", "enneagram_vote_id": 0, "mbti_vote": "", "mbti_vote_id": 0, "is_watching": false, "image_exists": false, "profile_image_url": "https://static1.personality-database.com/profile_images/757996043c054150b19885ca81638940.png", "profile_image_credit": "", "profile_image_credit_id": 217131, "profile_image_credit_type": "0", "profile_image_credit_url": "", "alt_subcategory": "", "related_subcategories": "", "cat_id": 13, "category": "Theatre", "category_is_fictional": true, "sub_cat_id": 20331, "subcategory": "Newsies (Musical)", "subcat_link_info": {"sub_cat_id": 20331, "cat_id": 13, "property_id": 2, "subcategory": "Newsies (Musical)"}, "related_subcat_link_info": null, "related_profiles": [{"id": 324964, "mbti_profile": "Jack Kelly", "subcategory": "Newsies (Musical)", "profile_image_url": "https://static1.personality-database.com/profile_images/6198d4c73f6849b59a34bbaa02247d53.png", "profile_name": "Jack Kelly", "profile_subcat": "Newsies (Musical)", "sub_cat_id": 20331, "cat_id": 13, "property_id": 2, "mbti": "ENTP", "enneatype": "7w8"}, {"id": 342405, "mbti_profile": "Nunzio", "subcategory": "Newsies (Musical)", "profile_image_url": "", "profile_name": "Nunzio", "profile_subcat": "Newsies (Musical)", "sub_cat_id": 20331, "cat_id": 13, "property_id": 2, "mbti": "INTJ", "enneatype": "5w4"}, {"id": 324965, "mbti_profile": "Charles Morris Albert (Crutchie)", "subcategory": "Newsies (Musical)", "profile_image_url": "https://static1.personality-database.com/profile_images/9db1658fbc1f4b71bca66dc686883a28.png", "profile_name": "Charles Morris Albert (Crutchie)", "profile_subcat": "Newsies (Musical)", "sub_cat_id": 20331, "cat_id": 13, "property_id": 2, "mbti": "ENFP", "enneatype": "6w7"}, {"id": 324972, "mbti_profile": "David Jacobs (Davey)", "subcategory": "Newsies (Musical)", "profile_image_url": "https://static1.personality-database.com/profile_images/c059fd53e9644471bc5618bf756fa863.png", "profile_name": "David Jacobs (Davey)", "profile_subcat": "Newsies (Musical)", "sub_cat_id": 20331, "cat_id": 13, "property_id": 2, "mbti": "INFJ", "enneatype": "6w5"}, {"id": 334833, "mbti_profile": "Racetrack Higgins", "subcategory": "Newsies (Musical)", "profile_image_url": "https://static1.personality-database.com/profile_images/4e7a961deae845f5966e7e4e07d1b9ab.png", "profile_name": "Racetrack Higgins", "profile_subcat": "Newsies (Musical)", "sub_cat_id": 20331, "cat_id": 13, "property_id": 2, "mbti": "ENTP", "enneatype": "7w8"}, {"id": 335089, "mbti_profile": "Spot Conlon", "subcategory": "Newsies (Musical)", "profile_image_url": "https://static1.personality-database.com/profile_images/cf27010e166c4a5caf63e28e9243abfb.png", "profile_name": "Spot Conlon", "profile_subcat": "Newsies (Musical)", "sub_cat_id": 20331, "cat_id": 13, "property_id": 2, "mbti": "ENTP", "enneatype": "3w4"}, {"id": 324967, "mbti_profile": "Joseph Pulitzer", "subcategory": "Newsies (Musical)", "profile_image_url": "https://static1.personality-database.com/profile_images/3de70032102f4a37a5b9e693d6480422.png", "profile_name": "Joseph Pulitzer", "profile_subcat": "Newsies (Musical)", "sub_cat_id": 20331, "cat_id": 13, "property_id": 2, "mbti": "ISTJ", "enneatype": "3w4"}, {"id": 324970, "mbti_profile": "Medda Larkin", "subcategory": "Newsies (Musical)", "profile_image_url": "https://static1.personality-database.com/profile_images/10d78e3f01e54e73af98e599eaea0f7e.png", "profile_name": "Medda Larkin", "profile_subcat": "Newsies (Musical)", "sub_cat_id": 20331, "cat_id": 13, "property_id": 2, "mbti": "ESFP", "enneatype": "3w4"}], "functions": ["Fe", "Ni", "Se", "Ti"], "systems": [{"hex_color": "#888888", "id": 1, "personality_type": "XXXX", "personality_type_id": 0, "system_name": "Four Letter", "system_vote_count": 24, "user_vote_type_id": 0, "vote_id": 0}, {"hex_color": "#006775", "id": 2, "personality_type": "XXXX", "personality_type_id": 0, "system_name": "Enneagram", "system_vote_count": 4, "user_vote_type_id": 0, "vote_id": 0}, {"hex_color": "#006775", "id": 5, "personality_type": "XXXX", "personality_type_id": 0, "system_name": "Instinctual Variant", "system_vote_count": 2, "user_vote_type_id": 0, "vote_id": 0}, {"hex_color": "#006775", "id": 6, "personality_type": "XXXX", "personality_type_id": 0, "system_name": "Tritype", "system_vote_count": 2, "user_vote_type_id": 0, "vote_id": 0}, {"hex_color": "#888888", "id": 3, "personality_type": "XXXX", "personality_type_id": 0, "system_name": "Socionics", "system_vote_count": 0, "user_vote_type_id": 0, "vote_id": 0}, {"hex_color": "#888888", "id": 9, "personality_type": "XXXX", "personality_type_id": 0, "system_name": "Big 5 (SLOAN)", "system_vote_count": 0, "user_vote_type_id": 0, "vote_id": 0}, {"hex_color": "#888888", "id": 8, "personality_type": "XXXX", "personality_type_id": 0, "system_name": "Attitudinal Psyche", "system_vote_count": 0, "user_vote_type_id": 0, "vote_id": 0}, {"hex_color": "#888888", "id": 7, "personality_type": "XXXX", "personality_type_id": 0, "system_name": "Temperaments", "system_vote_count": 3, "user_vote_type_id": 0, "vote_id": 0}, {"hex_color": "#888888", "id": 11, "personality_type": "XXXX", "personality_type_id": 0, "system_name": "Classic Jungian", "system_vote_count": 0, "user_vote_type_id": 0, "vote_id": 0}], "breakdown_systems": {"1": [{"myValue": "ENFJ", "personality_system_id": 1, "personality_type": "ENFJ", "theCount": 10}, {"myValue": "ESFJ", "personality_system_id": 1, "personality_type": "ESFJ", "theCount": 7}, {"myValue": "ENTJ", "personality_system_id": 1, "personality_type": "ENTJ", "theCount": 2}, {"myValue": "ENTP", "personality_system_id": 1, "personality_type": "ENTP", "theCount": 2}, {"myValue": "ENFP", "personality_system_id": 1, "personality_type": "ENFP", "theCount": 1}, {"myValue": "INFJ", "personality_system_id": 1, "personality_type": "INFJ", "theCount": 1}, {"myValue": "INTP", "personality_system_id": 1, "personality_type": "INTP", "theCount": 1}], "11": [{"myValue": "XXXX", "personality_system_id": 0, "personality_type": "XXXX", "theCount": 0}], "2": [{"myValue": "3w4", "personality_system_id": 2, "personality_type": "3w4", "theCount": 4}], "3": [{"myValue": "XXXX", "personality_system_id": 0, "personality_type": "XXXX", "theCount": 0}], "5": [{"myValue": "so/sp", "personality_system_id": 5, "personality_type": "so/sp", "theCount": 2}], "6": [{"myValue": "317", "personality_system_id": 6, "personality_type": "317", "theCount": 2}], "7": [{"myValue": "Sanguine [Dominant]", "personality_system_id": 7, "personality_type": "Sanguine [Dominant]", "theCount": 3}], "8": [{"myValue": "XXXX", "personality_system_id": 0, "personality_type": "XXXX", "theCount": 0}], "9": [{"myValue": "XXXX", "personality_system_id": 0, "personality_type": "XXXX", "theCount": 0}]}, "breakdown_config": {"expand": {"1": 3, "11": 1, "2": 3, "3": 1, "5": 1, "6": 1, "7": 1, "8": 1, "9": 1}, "fire": {"1": 0, "11": 0, "2": 0, "3": 0, "5": 0, "6": 0, "7": 0, "8": 0, "9": 0}}, "mbti_letter_stats": [{"type": "E", "percentage": "92%", "PercentageFloat": 0.9166666666666666}, {"type": "N", "percentage": "71%", "PercentageFloat": 0.7083333333333334}, {"type": "F", "percentage": "79%", "PercentageFloat": 0.7916666666666666}, {"type": "J", "percentage": "83%", "PercentageFloat": 0.8333333333333334}], "topic_info": {"can_generate": false, "topic": {"description": "", "follow_count": 0, "id": 250108, "is_following": false, "is_join_pending": false, "is_banned": false, "is_moderated": false, "name_readable": "Katherine", "post_count": 0, "source_profile_id": 324966, "source_type": "profile", "join_to_post": false, "can_pin": false, "related_topics": [{"description": "", "follow_count": 0, "id": 257751, "is_following": false, "is_join_pending": false, "is_banned": false, "is_moderated": false, "name_readable": "Racetrack Higgins", "post_count": 1, "source_profile_id": 334833, "source_type": "profile", "image": {"picURL": "https://static1.personality-database.com/profile_images/4e7a961deae845f5966e7e4e07d1b9ab.png"}, "join_to_post": false, "can_pin": false}, {"description": "Pulitzer\u2019s barber", "follow_count": 0, "id": 263539, "is_following": false, "is_join_pending": false, "is_banned": false, "is_moderated": false, "name_readable": "Nunzio", "post_count": 1, "source_profile_id": 342405, "source_type": "profile", "image": {"picURL": "https://www.personality-database.com/images/profile_transparent.png"}, "join_to_post": false, "can_pin": false}, {"description": "", "follow_count": 0, "id": 250106, "is_following": false, "is_join_pending": false, "is_banned": false, "is_moderated": false, "name_readable": "Jack Kelly", "post_count": 0, "source_profile_id": 324964, "source_type": "profile", "image": {"picURL": "https://static1.personality-database.com/profile_images/6198d4c73f6849b59a34bbaa02247d53.png"}, "join_to_post": false, "can_pin": false}, {"description": "", "follow_count": 0, "id": 250107, "is_following": false, "is_join_pending": false, "is_banned": false, "is_moderated": false, "name_readable": "Charles Morris Albert (Crutchie)", "post_count": 0, "source_profile_id": 324965, "source_type": "profile", "image": {"picURL": "https://static1.personality-database.com/profile_images/9db1658fbc1f4b71bca66dc686883a28.png"}, "join_to_post": false, "can_pin": false}, {"description": "", "follow_count": 0, "id": 250108, "is_following": false, "is_join_pending": false, "is_banned": false, "is_moderated": false, "name_readable": "Katherine", "post_count": 0, "source_profile_id": 324966, "source_type": "profile", "image": {"picURL": "https://static1.personality-database.com/profile_images/757996043c054150b19885ca81638940.png"}, "join_to_post": false, "can_pin": false}, {"description": "", "follow_count": 0, "id": 250109, "is_following": false, "is_join_pending": false, "is_banned": false, "is_moderated": false, "name_readable": "Joseph Pulitzer", "post_count": 0, "source_profile_id": 324967, "source_type": "profile", "image": {"picURL": "https://static1.personality-database.com/profile_images/3de70032102f4a37a5b9e693d6480422.png"}, "join_to_post": false, "can_pin": false}, {"description": "", "follow_count": 0, "id": 250110, "is_following": false, "is_join_pending": false, "is_banned": false, "is_moderated": false, "name_readable": "Medda Larkin", "post_count": 0, "source_profile_id": 324970, "source_type": "profile", "image": {"picURL": "https://static1.personality-database.com/profile_images/10d78e3f01e54e73af98e599eaea0f7e.png"}, "join_to_post": false, "can_pin": false}, {"description": "", "follow_count": 0, "id": 250111, "is_following": false, "is_join_pending": false, "is_banned": false, "is_moderated": false, "name_readable": "Les", "post_count": 0, "source_profile_id": 324971, "source_type": "profile", "image": {"picURL": "https://static1.personality-database.com/profile_images/2d4e8cb85b7a4d37a06b72db9857f3db.png"}, "join_to_post": false, "can_pin": false}, {"description": "", "follow_count": 0, "id": 250112, "is_following": false, "is_join_pending": false, "is_banned": false, "is_moderated": false, "name_readable": "David Jacobs (Davey)", "post_count": 0, "source_profile_id": 324972, "source_type": "profile", "image": {"picURL": "https://static1.personality-database.com/profile_images/c059fd53e9644471bc5618bf756fa863.png"}, "join_to_post": false, "can_pin": false}, {"description": "", "follow_count": 0, "id": 257959, "is_following": false, "is_join_pending": false, "is_banned": false, "is_moderated": false, "name_readable": "Spot Conlon", "post_count": 0, "source_profile_id": 335089, "source_type": "profile", "image": {"picURL": "https://static1.personality-database.com/profile_images/cf27010e166c4a5caf63e28e9243abfb.png"}, "join_to_post": false, "can_pin": false}], "subcategory": "Newsies (Musical)", "topic_image_url": "https://static1.personality-database.com/profile_images/757996043c054150b19885ca81638940.png", "source_location": {"cid": 13, "pid": 2, "sub_cat_id": 20331}, "can_post_image": false, "can_post_audio": false, "posts": {"posts": []}}}}