{"id": 37086, "mbti_profile": "Keefe Sencen", "profile_name_searchable": "keefesencen", "allow_commenting": true, "allow_voting": true, "user_id": 13320, "contributor": "addendumbeekeeper", "contributor_create_date": "2019-05-27 20:44:35", "contributor_pic_path": "https://lh3.googleusercontent.com/a-/AOh14GhHDFQaDwEhlDj6WY5DK2KpwxToAfidc-8HdSz5-DU=s96-c", "display_order": 0, "edit_lock": 0, "edit_lock_picture": 0, "is_active": true, "is_approved": true, "mbti_enneagram_type": "ENTP 7w8", "mbti_type": "ENTP 7w8", "pdb_comment_access": true, "pdb_page_owner": 0, "pdb_public_access": true, "wiki_description": "", "watch_count": 75, "comment_count": 116, "vote_count": 143, "vote_count_enneagram": 56, "vote_count_mbti": 143, "total_vote_counts": 257, "personality_type": "ENTP - 7w8 - sx/so - 738 - SLUAI - FLEV - Sanguine-Melancholic", "type_updated_date": "2022-05-02 00:36:58", "enneagram_vote": "", "enneagram_vote_id": 0, "mbti_vote": "", "mbti_vote_id": 0, "is_watching": false, "image_exists": false, "profile_image_url": "https://static1.personality-database.com/profile_images/a53ea18860c845d9890293664caff6e2.png", "profile_image_credit": "", "profile_image_credit_id": 194082, "profile_image_credit_type": "0", "profile_image_credit_url": "", "alt_subcategory": "", "related_subcategories": "", "cat_id": 12, "category": "Literature", "category_is_fictional": true, "sub_cat_id": 2693, "subcategory": "Keeper of the Lost Cities (Series)", "subcat_link_info": {"sub_cat_id": 2693, "cat_id": 12, "property_id": 2, "subcategory": "Keeper of the Lost Cities (Series)"}, "related_subcat_link_info": null, "related_profiles": [{"id": 24612, "mbti_profile": "Sophie Foster", "subcategory": "Keeper of the Lost Cities (Series)", "profile_image_url": "https://static1.personality-database.com/profile_images/1348a6127ca54e71b139452c241883c2.png", "profile_name": "Sophie Foster", "profile_subcat": "Keeper of the Lost Cities (Series)", "sub_cat_id": 2693, "cat_id": 12, "property_id": 2, "mbti": "ISFJ", "enneatype": "1w2"}, {"id": 40251, "mbti_profile": "Grady Ruewen", "subcategory": "Keeper of the Lost Cities (Series)", "profile_image_url": "https://static1.personality-database.com/profile_images/0d30d82884ec4af6a4a4e1d34ae55172.png", "profile_name": "Grady Ruewen", "profile_subcat": "Keeper of the Lost Cities (Series)", "sub_cat_id": 2693, "cat_id": 12, "property_id": 2, "mbti": "ESTP", "enneatype": ""}, {"id": 37087, "mbti_profile": "Fitz Vacker", "subcategory": "Keeper of the Lost Cities (Series)", "profile_image_url": "https://static1.personality-database.com/profile_images/1b64e22b0e5a47ecaf0fad0a953d1208.png", "profile_name": "Fitz Vacker", "profile_subcat": "Keeper of the Lost Cities (Series)", "sub_cat_id": 2693, "cat_id": 12, "property_id": 2, "mbti": "ESTJ", "enneatype": "3w2"}, {"id": 250668, "mbti_profile": "Lord Cassius", "subcategory": "Keeper of the Lost Cities (Series)", "profile_image_url": "https://static1.personality-database.com/profile_images/f632ae75e1294f239c908f68db814c01.png", "profile_name": "Lord Cassius", "profile_subcat": "Keeper of the Lost Cities (Series)", "sub_cat_id": 2693, "cat_id": 12, "property_id": 2, "mbti": "ESTJ", "enneatype": "3w4"}, {"id": 319818, "mbti_profile": "Fintan Pyren", "subcategory": "Keeper of the Lost Cities (Series)", "profile_image_url": "", "profile_name": "Fintan Pyren", "profile_subcat": "Keeper of the Lost Cities (Series)", "sub_cat_id": 2693, "cat_id": 12, "property_id": 2, "mbti": "INTJ", "enneatype": "8w7"}, {"id": 221092, "mbti_profile": "Kenric", "subcategory": "Keeper of the Lost Cities (Series)", "profile_image_url": "https://static1.personality-database.com/profile_images/fb969f8525b44fe99415daea3646f5db.png", "profile_name": "Kenric", "profile_subcat": "Keeper of the Lost Cities (Series)", "sub_cat_id": 2693, "cat_id": 12, "property_id": 2, "mbti": "ENFP", "enneatype": "7w8"}, {"id": 298865, "mbti_profile": "Alvar Vacker", "subcategory": "Keeper of the Lost Cities (Series)", "profile_image_url": "https://static1.personality-database.com/profile_images/987a79be45cb4d92b941e5c5a1572dca.png", "profile_name": "Alvar Vacker", "profile_subcat": "Keeper of the Lost Cities (Series)", "sub_cat_id": 2693, "cat_id": 12, "property_id": 2, "mbti": "INTJ", "enneatype": "3w4"}, {"id": 40351, "mbti_profile": "Edaline Ruewen", "subcategory": "Keeper of the Lost Cities (Series)", "profile_image_url": "https://static1.personality-database.com/profile_images/4d85ed53ceb34cff8eb8d696f57f063f.png", "profile_name": "Edaline Ruewen", "profile_subcat": "Keeper of the Lost Cities (Series)", "sub_cat_id": 2693, "cat_id": 12, "property_id": 2, "mbti": "ISFJ", "enneatype": "2w1"}], "functions": ["Ne", "Ti", "Fe", "Si"], "systems": [{"hex_color": "#888888", "id": 1, "personality_type": "XXXX", "personality_type_id": 0, "system_name": "Four Letter", "system_vote_count": 141, "user_vote_type_id": 0, "vote_id": 0}, {"hex_color": "#006775", "id": 2, "personality_type": "XXXX", "personality_type_id": 0, "system_name": "Enneagram", "system_vote_count": 54, "user_vote_type_id": 0, "vote_id": 0}, {"hex_color": "#006775", "id": 5, "personality_type": "XXXX", "personality_type_id": 0, "system_name": "Instinctual Variant", "system_vote_count": 18, "user_vote_type_id": 0, "vote_id": 0}, {"hex_color": "#006775", "id": 6, "personality_type": "XXXX", "personality_type_id": 0, "system_name": "Tritype", "system_vote_count": 15, "user_vote_type_id": 0, "vote_id": 0}, {"hex_color": "#888888", "id": 3, "personality_type": "XXXX", "personality_type_id": 0, "system_name": "Socionics", "system_vote_count": 0, "user_vote_type_id": 0, "vote_id": 0}, {"hex_color": "#888888", "id": 9, "personality_type": "XXXX", "personality_type_id": 0, "system_name": "Big 5 (SLOAN)", "system_vote_count": 5, "user_vote_type_id": 0, "vote_id": 0}, {"hex_color": "#888888", "id": 8, "personality_type": "XXXX", "personality_type_id": 0, "system_name": "Attitudinal Psyche", "system_vote_count": 1, "user_vote_type_id": 0, "vote_id": 0}, {"hex_color": "#888888", "id": 7, "personality_type": "XXXX", "personality_type_id": 0, "system_name": "Temperaments", "system_vote_count": 15, "user_vote_type_id": 0, "vote_id": 0}, {"hex_color": "#888888", "id": 11, "personality_type": "XXXX", "personality_type_id": 0, "system_name": "Classic Jungian", "system_vote_count": 1, "user_vote_type_id": 0, "vote_id": 0}], "breakdown_systems": {"1": [{"myValue": "ENTP", "personality_system_id": 1, "personality_type": "ENTP", "theCount": 81}, {"myValue": "ENFP", "personality_system_id": 1, "personality_type": "ENFP", "theCount": 54}, {"myValue": "ESTP", "personality_system_id": 1, "personality_type": "ESTP", "theCount": 2}, {"myValue": "INFJ", "personality_system_id": 1, "personality_type": "INFJ", "theCount": 2}, {"myValue": "ESFJ", "personality_system_id": 1, "personality_type": "ESFJ", "theCount": 1}, {"myValue": "ESFP", "personality_system_id": 1, "personality_type": "ESFP", "theCount": 1}], "11": [{"myValue": "EN(F)", "personality_system_id": 11, "personality_type": "EN(F)", "theCount": 1}], "2": [{"myValue": "7w8", "personality_system_id": 2, "personality_type": "7w8", "theCount": 42}, {"myValue": "7w6", "personality_system_id": 2, "personality_type": "7w6", "theCount": 11}, {"myValue": "6w7", "personality_system_id": 2, "personality_type": "6w7", "theCount": 1}], "3": [{"myValue": "XXXX", "personality_system_id": 0, "personality_type": "XXXX", "theCount": 0}], "4": [{"myValue": "Chaotic Good", "personality_system_id": 4, "personality_type": "Chaotic Good", "theCount": 7}], "5": [{"myValue": "sx/so", "personality_system_id": 5, "personality_type": "sx/so", "theCount": 7}, {"myValue": "so/sp", "personality_system_id": 5, "personality_type": "so/sp", "theCount": 5}, {"myValue": "so/sx", "personality_system_id": 5, "personality_type": "so/sx", "theCount": 3}, {"myValue": "sx/sp", "personality_system_id": 5, "personality_type": "sx/sp", "theCount": 3}], "6": [{"myValue": "738", "personality_system_id": 6, "personality_type": "738", "theCount": 6}, {"myValue": "728", "personality_system_id": 6, "personality_type": "728", "theCount": 5}, {"myValue": "783", "personality_system_id": 6, "personality_type": "783", "theCount": 3}, {"myValue": "748", "personality_system_id": 6, "personality_type": "748", "theCount": 1}], "7": [{"myValue": "Sanguine-Melancholic", "personality_system_id": 7, "personality_type": "Sanguine-Melancholic", "theCount": 8}, {"myValue": "Sanguine [Dominant]", "personality_system_id": 7, "personality_type": "Sanguine [Dominant]", "theCount": 6}, {"myValue": "Melancholic-Choleric", "personality_system_id": 7, "personality_type": "Melancholic-Choleric", "theCount": 1}], "8": [{"myValue": "FLEV", "personality_system_id": 8, "personality_type": "FLEV", "theCount": 1}], "9": [{"myValue": "SLUAI", "personality_system_id": 9, "personality_type": "SLUAI", "theCount": 3}, {"myValue": "SCUEI", "personality_system_id": 9, "personality_type": "SCUEI", "theCount": 1}, {"myValue": "SLUEN", "personality_system_id": 9, "personality_type": "SLUEN", "theCount": 1}]}, "breakdown_config": {"expand": {"1": 3, "11": 1, "2": 3, "3": 1, "4": 1, "5": 1, "6": 1, "7": 1, "8": 1, "9": 1}, "fire": {"1": 1, "11": 0, "2": 0, "3": 0, "4": 0, "5": 0, "6": 0, "7": 0, "8": 0, "9": 0}}, "mbti_letter_stats": [{"type": "E", "percentage": "99%", "PercentageFloat": 0.9858156028368794}, {"type": "N", "percentage": "97%", "PercentageFloat": 0.9716312056737588}, {"type": "T", "percentage": "59%", "PercentageFloat": 0.5886524822695035}, {"type": "P", "percentage": "98%", "PercentageFloat": 0.9787234042553191}], "topic_info": {"can_generate": false, "topic": {"description": "", "follow_count": 2, "id": 33148, "is_following": false, "is_join_pending": false, "is_banned": false, "is_moderated": false, "name_readable": "Keefe Sencen", "post_count": 5, "source_profile_id": 37086, "source_type": "profile", "join_to_post": false, "can_pin": false, "related_topics": [{"description": "", "follow_count": 2, "id": 33148, "is_following": false, "is_join_pending": false, "is_banned": false, "is_moderated": false, "name_readable": "Keefe Sencen", "post_count": 5, "source_profile_id": 37086, "source_type": "profile", "image": {"picURL": "https://static1.personality-database.com/profile_images/a53ea18860c845d9890293664caff6e2.png"}, "join_to_post": false, "can_pin": false}, {"description": "", "follow_count": 1, "id": 33151, "is_following": false, "is_join_pending": false, "is_banned": false, "is_moderated": false, "name_readable": "Tam Song", "post_count": 2, "source_profile_id": 37089, "source_type": "profile", "image": {"picURL": "https://static1.personality-database.com/profile_images/e5c6dd7f5d5342ff8e4036aa9c845c5a.png"}, "join_to_post": false, "can_pin": false}, {"description": "", "follow_count": 0, "id": 35861, "is_following": false, "is_join_pending": false, "is_banned": false, "is_moderated": false, "name_readable": "Grady Ruewen", "post_count": 2, "source_profile_id": 40251, "source_type": "profile", "image": {"picURL": "https://static1.personality-database.com/profile_images/0d30d82884ec4af6a4a4e1d34ae55172.png"}, "join_to_post": false, "can_pin": false}, {"description": "", "follow_count": 1, "id": 33152, "is_following": false, "is_join_pending": false, "is_banned": false, "is_moderated": false, "name_readable": "Dexter Dizznee", "post_count": 1, "source_profile_id": 37090, "source_type": "profile", "image": {"picURL": "https://static1.personality-database.com/profile_images/8dba0545b7794bbaac93e4655368a872.png"}, "join_to_post": false, "can_pin": false}, {"description": "", "follow_count": 0, "id": 190177, "is_following": false, "is_join_pending": false, "is_banned": false, "is_moderated": false, "name_readable": "Elwin Heslege", "post_count": 1, "source_profile_id": 246193, "source_type": "profile", "image": {"picURL": "https://static1.personality-database.com/profile_images/a09f266315d44806a7dbda7377e47593.png"}, "join_to_post": false, "can_pin": false}, {"description": "", "follow_count": 0, "id": 35946, "is_following": false, "is_join_pending": false, "is_banned": false, "is_moderated": false, "name_readable": "Stina Heks", "post_count": 1, "source_profile_id": 40350, "source_type": "profile", "image": {"picURL": "https://static1.personality-database.com/profile_images/e8d10fad1507401ebc8e04f361ee9b4e.png"}, "join_to_post": false, "can_pin": false}, {"description": "", "follow_count": 0, "id": 33740, "is_following": false, "is_join_pending": false, "is_banned": false, "is_moderated": false, "name_readable": "Marella Redek", "post_count": 1, "source_profile_id": 37744, "source_type": "profile", "image": {"picURL": "https://static1.personality-database.com/profile_images/2cef167e451b411c811e0bf90985f4de.png"}, "join_to_post": false, "can_pin": false}, {"description": "", "follow_count": 0, "id": 245827, "is_following": false, "is_join_pending": false, "is_banned": false, "is_moderated": false, "name_readable": "Fintan Pyren", "post_count": 1, "source_profile_id": 319818, "source_type": "profile", "image": {"picURL": "https://www.personality-database.com/images/profile_transparent.png"}, "join_to_post": false, "can_pin": false}, {"description": "", "follow_count": 0, "id": 248288, "is_following": false, "is_join_pending": false, "is_banned": false, "is_moderated": false, "name_readable": "Dimitar", "post_count": 0, "source_profile_id": 322743, "source_type": "profile", "image": {"picURL": "https://www.personality-database.com/images/profile_transparent.png"}, "join_to_post": false, "can_pin": false}, {"description": "", "follow_count": 0, "id": 242611, "is_following": false, "is_join_pending": false, "is_banned": false, "is_moderated": false, "name_readable": "Maruca Chebota", "post_count": 0, "source_profile_id": 315419, "source_type": "profile", "image": {"picURL": "https://static1.personality-database.com/profile_images/c4cdc19a586e4a3188a24332fd24781a.png"}, "join_to_post": false, "can_pin": false}, {"description": "", "follow_count": 0, "id": 266372, "is_following": false, "is_join_pending": false, "is_banned": false, "is_moderated": false, "name_readable": "Zillah", "post_count": 0, "source_profile_id": 346004, "source_type": "profile", "image": {"picURL": "https://www.personality-database.com/images/profile_transparent.png"}, "join_to_post": false, "can_pin": false}, {"description": "", "follow_count": 0, "id": 254520, "is_following": false, "is_join_pending": false, "is_banned": false, "is_moderated": false, "name_readable": "Terik", "post_count": 0, "source_profile_id": 330649, "source_type": "profile", "image": {"picURL": "https://static1.personality-database.com/profile_images/ba58d8d854e64f0b9a73034001f7897c.png"}, "join_to_post": false, "can_pin": false}, {"description": "", "follow_count": 0, "id": 254514, "is_following": false, "is_join_pending": false, "is_banned": false, "is_moderated": false, "name_readable": "Enki", "post_count": 0, "source_profile_id": 330642, "source_type": "profile", "image": {"picURL": "https://www.personality-database.com/images/profile_transparent.png"}, "join_to_post": false, "can_pin": false}, {"description": "", "follow_count": 0, "id": 248292, "is_following": false, "is_join_pending": false, "is_banned": false, "is_moderated": false, "name_readable": "Gethen Ondsinn", "post_count": 0, "source_profile_id": 322747, "source_type": "profile", "image": {"picURL": "https://www.personality-database.com/images/profile_transparent.png"}, "join_to_post": false, "can_pin": false}, {"description": "", "follow_count": 0, "id": 236655, "is_following": false, "is_join_pending": false, "is_banned": false, "is_moderated": false, "name_readable": "Prentice Endal", "post_count": 0, "source_profile_id": 307763, "source_type": "profile", "image": {"picURL": "https://static1.personality-database.com/profile_images/7f99a356c71d4c3eb8709dc4b1b214de.png"}, "join_to_post": false, "can_pin": false}, {"description": "", "follow_count": 0, "id": 245830, "is_following": false, "is_join_pending": false, "is_banned": false, "is_moderated": false, "name_readable": "Ruy Ignis", "post_count": 0, "source_profile_id": 319821, "source_type": "profile", "image": {"picURL": "https://www.personality-database.com/images/profile_transparent.png"}, "join_to_post": false, "can_pin": false}], "subcategory": "Keeper of the Lost Cities (Series)", "topic_image_url": "https://static1.personality-database.com/profile_images/a53ea18860c845d9890293664caff6e2.png", "source_location": {"cid": 12, "pid": 2, "sub_cat_id": 2693}, "can_post_image": false, "can_post_audio": false, "posts": {"posts": [{"username": "starlight_silence158159", "user_pic_path": "https://static1.personality-database.com/profile_images/42e02d07958d40379e5c200c5ab53ce0.png", "user_personality_type": "INFJ-2w1-296", "is_mod": false, "comment_count": 2, "reply_count": 2, "vote_type": 0, "topics_list": [{"id": 33148, "name_readable": "Keefe Sencen"}], "id": 2037828, "post_id": 2037828, "user_id": 1729251, "title": "Keefe should be a Feeler, not a Thinker. ", "content": "He doesn\u2019t actually base most of his decisions and choices off logic, he just hides his emotions so no one can get close to him, and he\u2019s afraid of people getting close because he doesn\u2019t want them to be disappointed in him. He actually cares about how Sophie is feeling and asks, unlike Fitz who just rages. And although abilities don\u2019t define people, he is an Empath, after all.", "create_date": 1672185352000, "unix_timestamp": 1672185352000, "update_date": 1672185352000, "vote_count": 1, "vote_count_down": 0, "is_reported": 0, "is_hidden": false, "is_pinned": false, "is_watching": false, "is_pro_user": false, "images": null, "audios": null, "function_list": [], "type": "post"}, {"username": "strange_and_unusual_13", "user_pic_path": "https://static1.personality-database.com/user_avatars/875387/1dab4daa-2e9b-4f90-a5c7-5fd836944562.jpeg", "user_personality_type": "ISTJ-1w9-163", "is_mod": false, "comment_count": 0, "reply_count": 0, "vote_type": 0, "topics_list": [{"id": 33148, "name_readable": "Keefe Sencen"}], "id": 1769384, "post_id": 1769384, "user_id": 875387, "title": "I thought I couldn\u2019t love him more but I was wrong\u2026.", "content": "Spoiler alert \ud83d\udea8 \nJust finished book 9!!\n-\n~\n-\n~ \n-\n~\n-\n~\n-\n~\n-\n~ \n-\n~\nI assume you have left if you don\u2019t want it spoiled now.\nIt was\u2026everything I dreamed\u2026Team Foster-Keefe forever! I\u2019m only sad there wasn\u2019t more time about their relationship\u2026.\nCut some of the Forkle talking about nothing and replace it with some Keefe teasing.", "create_date": 1668837937000, "unix_timestamp": 1668837937000, "update_date": 1668838051000, "vote_count": 3, "vote_count_down": 0, "is_reported": 0, "is_hidden": false, "is_pinned": false, "is_watching": false, "is_pro_user": false, "images": null, "audios": null, "function_list": [], "type": "post"}, {"username": "Sokeefe 4eva", "user_pic_path": "https://static1.personality-database.com/user_avatars/1331242/277155a2-a206-4c9d-b525-13d3633d4266.jpeg", "user_personality_type": "ENFJ-7w6", "is_mod": false, "comment_count": 2, "reply_count": 2, "vote_type": 0, "topics_list": [{"id": 33148, "name_readable": "Keefe Sencen"}], "id": 1657035, "post_id": 1657035, "user_id": 1331242, "title": "I'm so obsessed with the character!! He is the best and my biggest crush \ud83e\udd0d\ud83e\udd0d", "content": "#fandom", "create_date": 1667370353000, "unix_timestamp": 1667370353000, "update_date": 1667370353000, "vote_count": 1, "vote_count_down": 0, "is_reported": 0, "is_hidden": false, "is_pinned": false, "is_watching": false, "is_pro_user": false, "images": null, "audios": null, "function_list": [], "type": "post"}]}}}}